abacusSoftware/__GUI_images__.py
abacusSoftware/__about__.py
abacusSoftware/__init__.py
abacusSoftware/builtin.py
abacusSoftware/common.py
abacusSoftware/constants.py
abacusSoftware/exceptions.py
abacusSoftware/files.py
abacusSoftware/main.py
abacusSoftware/menuBar.py
abacusSoftware/supportWidgets.py
abacusSoftware/updateversion.py
abacusSoftware/url.py
abacusSoftware-1.6.1.dist-info/LICENSE
abacusSoftware-1.6.1.dist-info/METADATA
abacusSoftware-1.6.1.dist-info/WHEEL
abacusSoftware-1.6.1.dist-info/entry_points.txt
abacusSoftware-1.6.1.dist-info/top_level.txt
abacusSoftware-1.6.1.dist-info/RECORD
