Metadata-Version: 2.1
Name: abacusSoftware
Version: 1.6.1
Summary: Abacus Software is a suite of tools built to ensure your experience with Tausand's coincidence counters becomes simplified.
Home-page: https://github.com/Tausand-dev/AbacusSoftware
Author: Juan Barbosa
Author-email: js.barbosa10@uniandes.edu.co
Maintainer: David Guzman
Maintainer-email: da.guzman@outlook.com
License: GPL
Project-URL: Bug Tracker, https://github.com/Tausand-dev/AbacusSoftware/issues
Classifier: Development Status :: 5 - Production/Stable
Classifier: Topic :: Utilities
Classifier: License :: OSI Approved :: GNU General Public License (GPL)
Classifier: Operating System :: OS Independent
Classifier: Programming Language :: Python :: 3
Requires-Python: >=3.6
License-File: LICENSE
Requires-Dist: pyAbacus>=1.2
Requires-Dist: pyserial
Requires-Dist: numpy
Requires-Dist: pyqtgraph
Requires-Dist: PyQt5
Requires-Dist: qtmodern
